{
  "type": "minecraft:crafting_shaped",
  "category": "misc",
  "key": {
    "F": {
      "item": "reliquary:fertile_essence"
    },
    "R": {
      "item": "minecraft:rose_bush"
    },
    "S": {
      "item": "minecraft:stick"
    },
    "T": {
      "type": "neoforge:nbt",
      "item": "reliquary:void_tear",
      "strict": true,
      "tag": "{}"
    },
    "V": {
      "item": "minecraft:vine"
    }
  },
  "pattern": [
    " RF",
    "VTR",
    "SV "
  ],
  "result": {
    "item": "reliquary:harvest_rod"
  }
}